gto/__init__.py
gto/_gto_version.py
gto/_pydantic.py
gto/_version.py
gto/api.py
gto/base.py
gto/cli.py
gto/commit_message_generator.py
gto/config.py
gto/constants.py
gto/exceptions.py
gto/ext.py
gto/git_utils.py
gto/index.py
gto/log.py
gto/py.typed
gto/registry.py
gto/tag.py
gto/ui.py
gto/utils.py
gto/versions.py
tests/resources/__init__.py
tests/resources/sample_remote_repo_expected_history_churn.json
tests/resources/sample_remote_repo_expected_registry.json
gto-1.7.1.dist-info/LICENSE
gto-1.7.1.dist-info/METADATA
gto-1.7.1.dist-info/WHEEL
gto-1.7.1.dist-info/entry_points.txt
gto-1.7.1.dist-info/top_level.txt
gto-1.7.1.dist-info/RECORD
