Metadata-Version: 2.1
Name: gto
Version: 1.7.1
Summary: Version and deploy your models following GitOps principles
Download-URL: https://github.com/iterative/gto
Author: Alexander Guschin
Author-email: aguschin@iterative.ai
License: Apache License 2.0
Keywords: git repo repository artifact registry developer-tools collaboration
Classifier: Development Status :: 2 - Pre-Alpha
Classifier: Programming Language :: Python :: 3
Classifier: Programming Language :: Python :: 3.9
Classifier: Programming Language :: Python :: 3.10
Classifier: Programming Language :: Python :: 3.11
Requires-Python: >=3.9
License-File: LICENSE
Requires-Dist: scmrepo<4,>=3
Requires-Dist: typer>=0.4.1
Requires-Dist: rich
Requires-Dist: pydantic!=2.0.0,<3,>=1.9.0
Requires-Dist: ruamel.yaml
Requires-Dist: semver>=2.13.0
Requires-Dist: entrypoints
Requires-Dist: tabulate>=0.8.10
Requires-Dist: funcy
Provides-Extra: tests
Requires-Dist: pytest; extra == "tests"
Requires-Dist: pytest-cov; extra == "tests"
Requires-Dist: pytest-mock; extra == "tests"
Requires-Dist: pytest-test-utils; extra == "tests"
Requires-Dist: pylint==3.1.0; extra == "tests"
Requires-Dist: pylint-plugin-utils; extra == "tests"
Requires-Dist: freezegun; extra == "tests"
Requires-Dist: types-freezegun; extra == "tests"
